setup.py
python_treasury.egg-info/PKG-INFO
python_treasury.egg-info/SOURCES.txt
python_treasury.egg-info/dependency_links.txt
python_treasury.egg-info/top_level.txt
treasury/__init__.py