Metadata-Version: 1.0
Name: python-treasury
Version: 1.0a1
Summary: IBR Cold wallet library
Home-page: https://www.ibrb.org
Author: Cochise Ruhulessin
Author-email: c.ruhulessin@ibrb.org
License: UNKNOWN
Platform: UNKNOWN
